README.md
setup.py
ohlcvish/__init__.py
ohlcvish/__version__.py
ohlcvish/preprocess.py
ohlcvish.egg-info/PKG-INFO
ohlcvish.egg-info/SOURCES.txt
ohlcvish.egg-info/dependency_links.txt
ohlcvish.egg-info/requires.txt
ohlcvish.egg-info/top_level.txt