Metadata-Version: 2.1
Name: ohlcvish
Version: 0.0.1
Summary: analyse trading signals in OHLCV data
Home-page: https://github.com/terbeznik/ohlcvish
Author: Alexander Terbeznik
Author-email: alexander.terbeznik@gmail.com
License: UNKNOWN
Platform: UNKNOWN
Classifier: Programming Language :: Python :: 3
Classifier: License :: OSI Approved :: MIT License
Classifier: Operating System :: OS Independent
Requires-Python: >=3.6
